{"stats":{"minecraft:used":{"minecraft:carrot_on_a_stick":94,"minecraft:written_book":8},"minecraft:custom":{"minecraft:jump":57,"minecraft:time_since_rest":9703,"minecraft:damage_dealt":40,"minecraft:crouch_one_cm":2162,"minecraft:leave_game":1,"minecraft:sprint_one_cm":16261,"minecraft:play_time":9703,"minecraft:damage_taken":1020,"minecraft:time_since_death":9703,"minecraft:walk_one_cm":13572,"minecraft:sneak_time":1235,"minecraft:total_world_time":9703,"minecraft:fall_one_cm":3068,"minecraft:fly_one_cm":157578}},"DataVersion":3337}